README.md
setup.py
fortify_results/__init__.py
fortify_results/fortifyresults.py
fortify_results.egg-info/PKG-INFO
fortify_results.egg-info/SOURCES.txt
fortify_results.egg-info/dependency_links.txt
fortify_results.egg-info/entry_points.txt
fortify_results.egg-info/requires.txt
fortify_results.egg-info/top_level.txt